test/__init__.py
test/test_client_c1200.py
test/test_client_c6u.py
test/test_client_c80.py
test/test_client_deco.py
test/test_client_ex.py
test/test_client_mr.py
test/test_client_mr_200.py
test/test_client_re330.py
test/test_client_vr400v2.py
test/test_client_wdr.py
test/test_client_xdr.py
tplinkrouterc6u/__init__.py
tplinkrouterc6u/client_abstract.py
tplinkrouterc6u/provider.py
tplinkrouterc6u/client/__init__.py
tplinkrouterc6u/client/c1200.py
tplinkrouterc6u/client/c5400x.py
tplinkrouterc6u/client/c6u.py
tplinkrouterc6u/client/c80.py
tplinkrouterc6u/client/deco.py
tplinkrouterc6u/client/ex.py
tplinkrouterc6u/client/mr.py
tplinkrouterc6u/client/mr200.py
tplinkrouterc6u/client/re330.py
tplinkrouterc6u/client/vr.py
tplinkrouterc6u/client/vr400v2.py
tplinkrouterc6u/client/wdr.py
tplinkrouterc6u/client/xdr.py
tplinkrouterc6u/common/__init__.py
tplinkrouterc6u/common/dataclass.py
tplinkrouterc6u/common/encryption.py
tplinkrouterc6u/common/exception.py
tplinkrouterc6u/common/helper.py
tplinkrouterc6u/common/package_enum.py
tplinkrouterc6u-5.12.3.dist-info/licenses/LICENSE
tplinkrouterc6u-5.12.3.dist-info/METADATA
tplinkrouterc6u-5.12.3.dist-info/WHEEL
tplinkrouterc6u-5.12.3.dist-info/top_level.txt
tplinkrouterc6u-5.12.3.dist-info/RECORD
