Metadata-Version: 2.4
Name: tplinkrouterc6u
Version: 5.12.3
Summary: TP-Link Router API (supports also Mercusys Router)
Home-page: https://github.com/AlexandrErohin/TP-Link-Archer-C6U
Author: Alex Erohin
Author-email: alexanderErohin@yandex.ru
Classifier: License :: OSI Approved :: GNU General Public License v3 or later (GPLv3+)
Classifier: Operating System :: OS Independent
Classifier: Programming Language :: Python :: 3
Classifier: Programming Language :: Python :: 3.10
Classifier: Programming Language :: Python :: 3.11
Classifier: Programming Language :: Python :: 3.12
Classifier: Programming Language :: Python :: 3.13
Classifier: Programming Language :: Python :: 3.14
Classifier: Programming Language :: Python :: Implementation :: PyPy
Requires-Python: >=3.10
License-File: LICENSE
Requires-Dist: requests
Requires-Dist: pycryptodome
Requires-Dist: macaddress
Dynamic: author
Dynamic: author-email
Dynamic: classifier
Dynamic: description
Dynamic: description-content-type
Dynamic: home-page
Dynamic: license-file
Dynamic: requires-dist
Dynamic: requires-python
Dynamic: summary
